fourletterphat-0.1.0.dist-info/metadata.json
fourletterphat-0.1.0.dist-info/WHEEL
fourletterphat-0.1.0.dist-info/METADATA
fourletterphat-0.1.0.dist-info/DESCRIPTION.rst
fourletterphat-0.1.0.dist-info/top_level.txt
fourletterphat-0.1.0.dist-info/RECORD
fourletterphat/__init__.py
fourletterphat/i2c_bus.py
fourletterphat/HT16K33.py
fourletterphat/alphanum4.py
